__init__.py
interface.py
src/__init__.py
src/stats.py
src/utils.py
halfbrick_app_demo-0.1.1.dist-info/METADATA
halfbrick_app_demo-0.1.1.dist-info/WHEEL
halfbrick_app_demo-0.1.1.dist-info/entry_points.txt
halfbrick_app_demo-0.1.1.dist-info/top_level.txt
halfbrick_app_demo-0.1.1.dist-info/RECORD
