Metadata-Version: 2.1
Name: halfbrick-app-demo
Version: 0.1.1
Summary: UNKNOWN
Home-page: https://github.com/rachelwu21/halfbrick_app/
Author: Rachel Wu
License: UNKNOWN
Platform: UNKNOWN
Classifier: Programming Language :: Python :: 3
Classifier: Operating System :: OS Independent
